MANIFEST.in
README.md
setup.py
UW_EMS_Client.egg-info/PKG-INFO
UW_EMS_Client.egg-info/SOURCES.txt
UW_EMS_Client.egg-info/dependency_links.txt
UW_EMS_Client.egg-info/requires.txt
UW_EMS_Client.egg-info/top_level.txt
ems_client/VERSION
ems_client/__init__.py
ems_client/mock.py
ems_client/models.py
ems_client/service.py
ems_client/test.py
ems_client/tests.py
ems_client/management/__init__.py
ems_client/management/commands/__init__.py
ems_client/management/commands/ems.py
ems_client/resources/ems/file/EMSAPI/Service.asmx_WSDL
ems_client/resources/ems/file/ServiceSoap/GetAPIVersion/99914B932BD37A50B983C5E7C90AE93B
ems_client/resources/ems/file/ServiceSoap/GetAllRooms/58B9D6D0D1CD6AD798E4D04E5C1BEC8B
ems_client/resources/ems/file/ServiceSoap/GetAreas/2A4561B4AD9B3708C5AC287255D333E1
ems_client/resources/ems/file/ServiceSoap/GetBooking/D37DA137FBB9AE76BD2B6754923C9582
ems_client/resources/ems/file/ServiceSoap/GetBooking/EC40C4B103B573BEF57B35EBB5763E5F
ems_client/resources/ems/file/ServiceSoap/GetBookings/6780F4C71AE818533465927BDCE232AF
ems_client/resources/ems/file/ServiceSoap/GetBookings/7D97DA76F7D9FFCB10AB0C53961E44C3
ems_client/resources/ems/file/ServiceSoap/GetBookings2/120E4EF9D3AA66AF1B250556DD1F8BE5
ems_client/resources/ems/file/ServiceSoap/GetBookings2/6BE84F2001FD9C46FEEB7E3C8644342F
ems_client/resources/ems/file/ServiceSoap/GetBuildings/99914B932BD37A50B983C5E7C90AE93B
ems_client/resources/ems/file/ServiceSoap/GetChangedBookings/75C68CC9ABAE4FAB725CB8FF64C16615
ems_client/resources/ems/file/ServiceSoap/GetEventTypes/99914B932BD37A50B983C5E7C90AE93B
ems_client/resources/ems/file/ServiceSoap/GetServiceOrderDetails/27923C8E39741B2003314324BD737511
ems_client/resources/ems/file/ServiceSoap/GetServiceOrderDetails/79EEAF6960F894D5AF83CF6DFEA59D30
ems_client/resources/ems/file/ServiceSoap/GetStatuses/99914B932BD37A50B983C5E7C90AE93B